<MaterialEntry>
	<Key>BasicMissileAssembler</Key>
	<Pages>
		<Page>
			<Paragraphs>
				<Title>
					<Text>Einfacher Raketenfertiger</Text>
				</Title>
				<Icon>
					<Name>Basic Missile Assembler</Name>
					<Alignment>Center</Alignment>
				</Icon>
				<Paragraph>
					<Text>Der Raketenfertiger ist eine Maschine die zur Produktion von Raketen verwendet wird.</Text>
				</Paragraph>
				<Header>
					<Text>Verwendung</Text>
				</Header>
				<Paragraph>
					<Text>Wie bei allen eigenständigen Produktionsmaschinen solltest du einen Trichter davor platzieren der die Einstellung &#34;nur auslagern&#34; hat. Das stellt sicher das die Produktion nicht aufgrung eines Mangels einer Ressource dauerhaft blockiert wird.</Text>
				</Paragraph>
				<Spacer/>
				<Paragraph>
					<Text>Jede Rakete benötigt 1 Kupfer Rohr, 1 Gold Draht und 1 H.E.C.F. (High Energy Composite Fuel).</Text>
				</Paragraph>
				<Spacer/>
				<Paragraph>
					<Text>Die Maschine benötigt außerdem Energie, die von einem angeschlossenen Erzeuger oder indirekt, mittels Laser Transmittern oder Speicherblöcken, bereitgestellt werden kann.</Text>
				</Paragraph>
				<Spacer/>
				<Paragraph>
					<Text>Energieblöcke und Trichter können nicht nur auf den Seiten sondern auch an der unteren und oberen Fläche der Maschine platziert werden.</Text>
				</Paragraph>
			</Paragraphs>
		</Page>
				
	</Pages>
</MaterialEntry>
