<MaterialEntry>
	<Name>Advanced machine block</Name>
	<Pages>
		<Page>
			<Paragraphs>
				<Title>
					<Text>Усовершенствованный Машинный Блок</Text>
				</Title>
				<Icon>
					<Name>Advanced machine block</Name>
					<Alignment>Center</Alignment>
				</Icon>
				<Paragraph>
					<Text>Основной блок Усовершенствованных Машин.</Text>
				</Paragraph>
				<Header>
					<Text>Эти блоки являются компонентом некоторого многоблочного оборудования.</Text>
				</Header>
			</Paragraphs>
		</Page>
				
	</Pages>
</MaterialEntry>

