<Chapter>
	<Handle>suit upgrades</Handle>
	<Title>Amélioration de Combinaison</Title>
	<Icon>Suit Upgrading</Icon>
	<Pages>
		<Page>
			<Paragraphs>
				<Title>
					<Text>Amélioration de Combinaison</Text>
				</Title>
				<Icon>
					<Name>SuitUpgrades</Name>
					<Alignment>Center</Alignment>
				</Icon>
				<Paragraph>
					<Text>&quot;Votre combinaison environnementale est une pièce d\&apos;ingénierie la plus avancée connue de l\&apos;homme. Malheureusement, son utilité dépend d\&apos;un système de mise à niveau par modules  au-delà de nos capacités de fabrication actuelles. Il est temps de se pencher sur la façon dont vous pouvez créer vos propres améliorations loin des usines. Vous pouvez utiliser un peu d\&apos;aide pour survivre dans cet environnement hostile.&quot;</Text>
				</Paragraph>
			</Paragraphs>
		</Page>
	</Pages>
</Chapter>
