<Chapter>
	<Handle>mining upgrade 3</Handle>
	<Title>Tussenliggende Mijnbouwverbeteringen I</Title>
	<Icon>Ore Smelter</Icon>
	<Pages>
		<Page>
			<Paragraphs>
				<Title>
					<Text>Tussenliggende Mijnbouwverbeteringen I</Text>
				</Title>
				<Icon>
					<Name>Ore Smelter</Name>
					<Alignment>Center</Alignment>
				</Icon>
				<Paragraph>
					<Text>We hebben met succes een nieuwe Ertssmeltoven ontworpen. Dit zal sommige geavanceerde materialen nodig hebben die zich niet in de buurt van het oppervlak bevinden.</Text>
				</Paragraph>
			</Paragraphs>
		</Page>
	</Pages>
</Chapter>
