<Chapter>
	<Handle>Advanced Defence</Handle>
	<Title>Defensa Avanzada</Title>
	<Icon>&gt;Missile Turret MK1</Icon>
	<Pages>
		<Page>
			<Paragraphs>
				<Title>
					<Text>Defensa Avanzada</Text>
				</Title>
				<Icon>
					<Name>Missile Turret MK1</Name>
					<Alignment>Center</Alignment>
				</Icon>
				<Paragraph>
					<Text>Hemos diseñado con éxito las torres de misiles y realizamos más mejoras en la torreta de energía. ¡Tendremos que fabricar misiles y esto requerirá un suministro de combustible!</Text>
  
				</Paragraph>
			</Paragraphs>
		</Page>
	</Pages>
</Chapter>
